README.txt
setup.cfg
setup.py
django_unittest_depth.egg-info/PKG-INFO
django_unittest_depth.egg-info/SOURCES.txt
django_unittest_depth.egg-info/dependency_links.txt
django_unittest_depth.egg-info/top_level.txt
djangox/__init__.py
djangox/test/__init__.py
djangox/test/depth.py