Metadata-Version: 1.0
Name: django-unittest-depth
Version: 0.4
Summary: Run django unittest recursively
Home-page: http://pypi.python.org/pypi/django-unittest-depth/
Author: Ask Solem
Author-email: askh@opera.com
License: UNKNOWN
Platform: UNKNOWN
Classifier: Development Status :: 3 - Alpha
Classifier: Intended Audience :: Developers
Classifier: License :: OSI Approved :: GNU General Public License (GPL)
Classifier: Operating System :: OS Independent
Classifier: Programming Language :: Python
